Metadata-Version: 2.1
Name: lsudt
Version: 0.2.2
Summary: Utility to list USB devices including associated Linux devices
Home-page: https://github.com/The-Good-Penguin/lsudt
Author: Andrew Murray
Author-email: amurray@thegoodpenguin.co.uk
License: GPLv2
Keywords: usb list devices lsusb udev pyudev
Platform: UNKNOWN
Classifier: Development Status :: 3 - Alpha
Classifier: Environment :: Console
Classifier: Intended Audience :: Developers
Classifier: Intended Audience :: End Users/Desktop
Classifier: Intended Audience :: Information Technology
Classifier: Intended Audience :: System Administrators
Classifier: License :: OSI Approved :: GNU General Public License v2 (GPLv2)
Classifier: Natural Language :: English
Classifier: Operating System :: POSIX :: Linux
Classifier: Programming Language :: Python
Classifier: Topic :: Software Development :: Embedded Systems
Classifier: Topic :: System :: Hardware :: Universal Serial Bus (USB)
Classifier: Topic :: System :: Systems Administration
Classifier: Topic :: Utilities
Requires-Python: >=3.6
License-File: LICENSE
